bmlibrarian_lite/__init__.py
bmlibrarian_lite/__main__.py
bmlibrarian_lite/chunking.py
bmlibrarian_lite/cli.py
bmlibrarian_lite/config.py
bmlibrarian_lite/constants.py
bmlibrarian_lite/conversation_export.py
bmlibrarian_lite/data_models.py
bmlibrarian_lite/embeddings.py
bmlibrarian_lite/europepmc.py
bmlibrarian_lite/exceptions.py
bmlibrarian_lite/fulltext_discovery.py
bmlibrarian_lite/pdf_discovery.py
bmlibrarian_lite/pdf_utils.py
bmlibrarian_lite/query_converter.py
bmlibrarian_lite/storage.py
bmlibrarian_lite/utils.py
bmlibrarian_lite/agents/__init__.py
bmlibrarian_lite/agents/base.py
bmlibrarian_lite/agents/citation_agent.py
bmlibrarian_lite/agents/interrogation_agent.py
bmlibrarian_lite/agents/reporting_agent.py
bmlibrarian_lite/agents/scoring_agent.py
bmlibrarian_lite/agents/search_agent.py
bmlibrarian_lite/benchmarking/__init__.py
bmlibrarian_lite/benchmarking/models.py
bmlibrarian_lite/benchmarking/quality_models.py
bmlibrarian_lite/benchmarking/quality_runner.py
bmlibrarian_lite/benchmarking/quality_statistics.py
bmlibrarian_lite/benchmarking/runner.py
bmlibrarian_lite/benchmarking/statistics.py
bmlibrarian_lite/gui/__init__.py
bmlibrarian_lite/gui/app.py
bmlibrarian_lite/gui/audit_citations_tab.py
bmlibrarian_lite/gui/audit_literature_tab.py
bmlibrarian_lite/gui/audit_queries_tab.py
bmlibrarian_lite/gui/audit_trail_tab.py
bmlibrarian_lite/gui/benchmark_dialog.py
bmlibrarian_lite/gui/benchmark_results_dialog.py
bmlibrarian_lite/gui/card_utils.py
bmlibrarian_lite/gui/chat_widgets.py
bmlibrarian_lite/gui/citation_loader.py
bmlibrarian_lite/gui/dialogs.py
bmlibrarian_lite/gui/document_card.py
bmlibrarian_lite/gui/document_interrogation_tab.py
bmlibrarian_lite/gui/document_viewer.py
bmlibrarian_lite/gui/quality_badge.py
bmlibrarian_lite/gui/quality_benchmark_dialog.py
bmlibrarian_lite/gui/quality_benchmark_results_dialog.py
bmlibrarian_lite/gui/quality_filter_panel.py
bmlibrarian_lite/gui/quality_summary.py
bmlibrarian_lite/gui/report_tab.py
bmlibrarian_lite-0.2.0.dist-info/METADATA
bmlibrarian_lite-0.2.0.dist-info/WHEEL
bmlibrarian_lite-0.2.0.dist-info/entry_points.txt
bmlibrarian_lite-0.2.0.dist-info/licenses/LICENSE
bmlibrarian_lite-0.2.0.dist-info/RECORD
