Metadata-Version: 2.4
Name: bmlibrarian-lite
Version: 0.2.0
Summary: Lightweight biomedical literature research tool - no PostgreSQL required
Project-URL: Homepage, https://github.com/hherb/bmlibrarian_lite
Project-URL: Documentation, https://github.com/hherb/bmlibrarian_lite#readme
Project-URL: Repository, https://github.com/hherb/bmlibrarian_lite.git
Project-URL: Issues, https://github.com/hherb/bmlibrarian_lite/issues
Author-email: Horst Herb <bmlibrarian@proton.me>
License: GPL-3.0-or-later
License-File: LICENSE
Keywords: ai,biomedical,literature,llm,pubmed,research,systematic-review
Classifier: Development Status :: 4 - Beta
Classifier: Intended Audience :: Healthcare Industry
Classifier: Intended Audience :: Science/Research
Classifier: License :: OSI Approved :: GNU General Public License v3 or later (GPLv3+)
Classifier: Operating System :: OS Independent
Classifier: Programming Language :: Python :: 3
Classifier: Programming Language :: Python :: 3.12
Classifier: Programming Language :: Python :: 3.13
Classifier: Topic :: Scientific/Engineering :: Information Analysis
Classifier: Topic :: Scientific/Engineering :: Medical Science Apps.
Requires-Python: >=3.12
Requires-Dist: anthropic>=0.34.0
Requires-Dist: backoff>=2.2.1
Requires-Dist: fastembed>=0.3.0
Requires-Dist: markdown>=3.5.0
Requires-Dist: ollama>=0.3.0
Requires-Dist: pygments>=2.17.0
Requires-Dist: pymupdf>=1.23.0
Requires-Dist: pysbd>=0.3.4
Requires-Dist: pyside6>=6.6.0
Requires-Dist: python-dotenv>=1.0.0
Requires-Dist: requests>=2.31.0
Requires-Dist: sqlite-vec>=0.1.6
Requires-Dist: tenacity>=8.2.0
Requires-Dist: tokenizers>=0.19.0
Provides-Extra: dev
Requires-Dist: mypy>=1.9.0; extra == 'dev'
Requires-Dist: pytest-cov>=4.1.0; extra == 'dev'
Requires-Dist: pytest>=8.0.0; extra == 'dev'
Requires-Dist: ruff>=0.4.0; extra == 'dev'
